riskscore/__init__.py
riskscore/creditscore.py
riskscore/mechinelearning.py
riskscore-0.0.4.dist-info/LICENSE
riskscore-0.0.4.dist-info/METADATA
riskscore-0.0.4.dist-info/WHEEL
riskscore-0.0.4.dist-info/entry_points.txt
riskscore-0.0.4.dist-info/top_level.txt
riskscore-0.0.4.dist-info/RECORD
